CHANGES.rst
CONTRIBUTORS.rst
DEVELOP.rst
LICENSE.GPL
LICENSE.rst
MANIFEST.in
README.rst
constraints.txt
constraints_plone50.txt
constraints_plone51.txt
constraints_plone52.txt
requirements.txt
setup.cfg
setup.py
tox.ini
docs/conf.py
docs/index.rst
src/cs/__init__.py
src/cs.behavior.footerhtmlcode.egg-info/PKG-INFO
src/cs.behavior.footerhtmlcode.egg-info/SOURCES.txt
src/cs.behavior.footerhtmlcode.egg-info/dependency_links.txt
src/cs.behavior.footerhtmlcode.egg-info/entry_points.txt
src/cs.behavior.footerhtmlcode.egg-info/namespace_packages.txt
src/cs.behavior.footerhtmlcode.egg-info/not-zip-safe
src/cs.behavior.footerhtmlcode.egg-info/requires.txt
src/cs.behavior.footerhtmlcode.egg-info/top_level.txt
src/cs/behavior/__init__.py
src/cs/behavior/footerhtmlcode/__init__.py
src/cs/behavior/footerhtmlcode/configure.zcml
src/cs/behavior/footerhtmlcode/interfaces.py
src/cs/behavior/footerhtmlcode/permissions.zcml
src/cs/behavior/footerhtmlcode/setuphandlers.py
src/cs/behavior/footerhtmlcode/testing.py
src/cs/behavior/footerhtmlcode/upgrades.py
src/cs/behavior/footerhtmlcode/upgrades.zcml
src/cs/behavior/footerhtmlcode/behaviors/__init__.py
src/cs/behavior/footerhtmlcode/behaviors/configure.zcml
src/cs/behavior/footerhtmlcode/behaviors/footer_html_code.py
src/cs/behavior/footerhtmlcode/locales/README.rst
src/cs/behavior/footerhtmlcode/locales/__init__.py
src/cs/behavior/footerhtmlcode/locales/cs.behavior.footerhtmlcode.pot
src/cs/behavior/footerhtmlcode/locales/update.py
src/cs/behavior/footerhtmlcode/locales/update.sh
src/cs/behavior/footerhtmlcode/locales/en/LC_MESSAGES/cs.behavior.footerhtmlcode.mo
src/cs/behavior/footerhtmlcode/locales/en/LC_MESSAGES/cs.behavior.footerhtmlcode.po
src/cs/behavior/footerhtmlcode/profiles/default/browserlayer.xml
src/cs/behavior/footerhtmlcode/profiles/default/catalog.xml
src/cs/behavior/footerhtmlcode/profiles/default/metadata.xml
src/cs/behavior/footerhtmlcode/profiles/default/registry.xml
src/cs/behavior/footerhtmlcode/profiles/default/rolemap.xml
src/cs/behavior/footerhtmlcode/profiles/default/types.xml
src/cs/behavior/footerhtmlcode/profiles/default/types/LRF.xml
src/cs/behavior/footerhtmlcode/profiles/uninstall/browserlayer.xml
src/cs/behavior/footerhtmlcode/tests/__init__.py
src/cs/behavior/footerhtmlcode/tests/test_behavior_footer_h_t_m_l_code.py
src/cs/behavior/footerhtmlcode/tests/test_setup.py
