Metadata-Version: 2.1
Name: cs.behavior.footerhtmlcode
Version: 1.0
Summary: An add-on providing a behavior that allows entering arbitrary HTML code to be shown in a portlet in LRF objects
Home-page: https://github.com/codesyntax/cs.behavior.footerhtmlcode
Author: Mikel Larreategi
Author-email: mlarreategi@codesyntax.com
License: GPL version 2
Project-URL: Source, https://github.com/codesyntax/cs.behavior.footerhtmlcode
Project-URL: Tracker, https://github.com/codesyntax/cs.behavior.footerhtmlcode/issues
Project-URL: PyPI, https://pypi.python.org/pypi/cs.behavior.footerhtmlcode
Keywords: Python Plone
Platform: UNKNOWN
Classifier: Environment :: Web Environment
Classifier: Framework :: Plone
Classifier: Framework :: Plone :: Addon
Classifier: Framework :: Plone :: 5.1
Classifier: Framework :: Plone :: 5.2
Classifier: Programming Language :: Python
Classifier: Programming Language :: Python :: 2.7
Classifier: Programming Language :: Python :: 3.6
Classifier: Programming Language :: Python :: 3.7
Classifier: Operating System :: OS Independent
Classifier: License :: OSI Approved :: GNU General Public License v2 (GPLv2)
Requires-Python: ==2.7
Provides-Extra: test
